AUTHORS
LICENSE
MANIFEST.in
README.rst
setup.py
debug_logging/__init__.py
debug_logging/admin.py
debug_logging/formatters.py
debug_logging/handlers.py
debug_logging/middleware.py
debug_logging/models.py
debug_logging/settings.py
debug_logging/urls.py
debug_logging/utils.py
debug_logging/views.py
debug_logging/management/__init__.py
debug_logging/management/commands/__init__.py
debug_logging/management/commands/log_urls.py
debug_logging/migrations/0001_initial.py
debug_logging/migrations/0002_add_test_run_model.py
debug_logging/migrations/0003_move_project_name_hostname_revision.py
debug_logging/migrations/0004_remove_project_name_hostname_revision.py
debug_logging/migrations/0005_rename_picklefields.py
debug_logging/migrations/0006_auto__change_test_run_end.py
debug_logging/migrations/0007_auto__add_field_testrun_name__add_field_testrun_description.py
debug_logging/migrations/0008_auto__add_field_testrun_total_requests.py
debug_logging/migrations/__init__.py
debug_logging/panels/__init__.py
debug_logging/panels/cache.py
debug_logging/panels/identity.py
debug_logging/panels/revision.py
debug_logging/panels/settings_vars.py
debug_logging/panels/sql.py
debug_logging/panels/timer.py
debug_logging/static/debug_logging/css/basic.css
debug_logging/static/debug_logging/css/rtd.css
debug_logging/static/debug_logging/css/style.css
debug_logging/static/debug_logging/img/search.png
debug_logging/static/debug_logging/js/expandable.js
debug_logging/static/debug_logging/js/highlights.js
debug_logging/static/debug_logging/js/test_run.js
debug_logging/static/debug_logging/js/lib/jquery-1.5.1.min.js
debug_logging/templates/debug_logging/_inline_record.html
debug_logging/templates/debug_logging/base.html
debug_logging/templates/debug_logging/index.html
debug_logging/templates/debug_logging/record_detail.html
debug_logging/templates/debug_logging/run_detail.html
django_debug_logging.egg-info/PKG-INFO
django_debug_logging.egg-info/SOURCES.txt
django_debug_logging.egg-info/dependency_links.txt
django_debug_logging.egg-info/not-zip-safe
django_debug_logging.egg-info/requires.txt
django_debug_logging.egg-info/top_level.txt