Metadata-Version: 1.0
Name: django-debug-logging
Version: 0.4
Summary: A plugin for django_debug_toolbar that logs results to the database for aggregated review.
Home-page: http://lincolnloop.github.com/django-debug-logging/
Author: Brandon Konkle
Author-email: brandon@lincolnloop.com
License: BSD
Download-URL: http://github.com/lincolnloop/django-debug-logging/downloads
Platform: UNKNOWN
Classifier: Development Status :: 4 - Beta
Classifier: Environment :: Web Environment
Classifier: Framework :: Django
Classifier: Intended Audience :: Developers
Classifier: License :: OSI Approved :: BSD License
Classifier: Operating System :: OS Independent
Classifier: Programming Language :: Python
Classifier: Topic :: Software Development :: Libraries :: Python Modules
